{
  "DName": "Save",
  "DSize": 13,
  "DSource": "C:\\www\\WPF",
  "DTarget": "C:\\www\\WPF_Backup",
  "DTime": "00:00:00.05",
  "DTransferTime": null,
  "FileName": null,
  "FileSize": null,
  "SourceFolder": null,
  "TargetFolder": null,
  "DateBackup": "14/12/2021 10:15:00",
  "SaveTime": null
}
{
  "DName": "Save",
  "DSize": 13,
  "DSource": "C:\\www\\WPF",
  "DTarget": "C:\\www\\WPF_Backup",
  "DTime": "00:00:00.01",
  "DTransferTime": null,
  "FileName": null,
  "FileSize": null,
  "SourceFolder": null,
  "TargetFolder": null,
  "DateBackup": "14/12/2021 10:22:11",
  "SaveTime": null
}
{
  "DName": "Aled",
  "DSize": 124958,
  "DSource": "C:\\www\\Aled",
  "DTarget": "C:\\www\\Aled_Backup",
  "DTime": "00:00:00.15",
  "DTransferTime": null,
  "FileName": null,
  "FileSize": null,
  "SourceFolder": null,
  "TargetFolder": null,
  "DateBackup": "14/12/2021 10:29:04",
  "SaveTime": null
}
{
  "DName": "Aled",
  "DSize": 466078,
  "DSource": "C:\\www\\Aled",
  "DTarget": "C:\\www\\Aled_Backup",
  "DTime": "00:00:00.03",
  "DTransferTime": null,
  "FileName": null,
  "FileSize": null,
  "SourceFolder": null,
  "TargetFolder": null,
  "DateBackup": "14/12/2021 10:29:44",
  "SaveTime": null
}
{
  "DName": "Aled",
  "DSize": 466078,
  "DSource": "C:\\www\\Aled",
  "DTarget": "C:\\www\\Aled_Backup",
  "DTime": "00:00:00.01",
  "DTransferTime": null,
  "FileName": null,
  "FileSize": null,
  "SourceFolder": null,
  "TargetFolder": null,
  "DateBackup": "14/12/2021 10:29:59",
  "SaveTime": null
}
{
  "DName": "Aled",
  "DSize": 1489438,
  "DSource": "C:\\www\\Aled",
  "DTarget": "C:\\www\\Aled_Backup",
  "DTime": "00:00:00.01",
  "DTransferTime": null,
  "FileName": null,
  "FileSize": null,
  "SourceFolder": null,
  "TargetFolder": null,
  "DateBackup": "14/12/2021 10:30:36",
  "SaveTime": null
}
{
  "DName": "Aled",
  "DSize": 1489438,
  "DSource": "C:\\www\\Aled",
  "DTarget": "C:\\www\\Aled_Backup",
  "DTime": "00:01:51.02",
  "DTransferTime": null,
  "FileName": null,
  "FileSize": null,
  "SourceFolder": null,
  "TargetFolder": null,
  "DateBackup": "14/12/2021 10:37:20",
  "SaveTime": null
}
{
  "DName": "Aled",
  "DSize": 112869,
  "DSource": "C:\\www\\Aled",
  "DTarget": "C:\\www\\Aled_Backup",
  "DTime": "00:00:00.02",
  "DTransferTime": null,
  "FileName": null,
  "FileSize": null,
  "SourceFolder": null,
  "TargetFolder": null,
  "DateBackup": "14/12/2021 10:37:41",
  "SaveTime": null
}
{
  "DName": "Aled",
  "DSize": 112869,
  "DSource": "C:\\www\\Aled",
  "DTarget": "C:\\www\\Aled_Backup",
  "DTime": "00:00:00.06",
  "DTransferTime": null,
  "FileName": null,
  "FileSize": null,
  "SourceFolder": null,
  "TargetFolder": null,
  "DateBackup": "14/12/2021 10:39:28",
  "SaveTime": null
}
{
  "DName": "Save",
  "DSize": 169766322,
  "DSource": "C:\\www\\WPF",
  "DTarget": "C:\\www\\WPF_Backup",
  "DTime": "00:00:18.88",
  "DTransferTime": null,
  "FileName": null,
  "FileSize": null,
  "SourceFolder": null,
  "TargetFolder": null,
  "DateBackup": "14/12/2021 10:42:13",
  "SaveTime": null
}
{
  "DName": "Aled",
  "DSize": 112869,
  "DSource": "C:\\www\\Aled",
  "DTarget": "C:\\www\\Aled_Backup",
  "DTime": "00:00:00.08",
  "DTransferTime": null,
  "FileName": null,
  "FileSize": null,
  "SourceFolder": null,
  "TargetFolder": null,
  "DateBackup": "14/12/2021 11:20:57",
  "SaveTime": null
}
{
  "DName": "Aled",
  "DSize": 112869,
  "DSource": "C:\\www\\Aled",
  "DTarget": "C:\\www\\Aled_Backup",
  "DTime": "00:00:00.07",
  "DTransferTime": null,
  "FileName": null,
  "FileSize": null,
  "SourceFolder": null,
  "TargetFolder": null,
  "DateBackup": "14/12/2021 11:21:28",
  "SaveTime": null
}
{
  "DName": "Aled",
  "DSize": 112869,
  "DSource": "C:\\www\\Aled",
  "DTarget": "C:\\www\\Aled_Backup",
  "DTime": "00:00:00.07",
  "DTransferTime": null,
  "FileName": null,
  "FileSize": null,
  "SourceFolder": null,
  "TargetFolder": null,
  "DateBackup": "14/12/2021 11:22:06",
  "SaveTime": null
}
{
  "DName": "Aled",
  "DSize": 164568044,
  "DSource": "C:\\www\\Aled",
  "DTarget": "C:\\www\\Aled_Backup",
  "DTime": "00:00:00.30",
  "DTransferTime": null,
  "FileName": null,
  "FileSize": null,
  "SourceFolder": null,
  "TargetFolder": null,
  "DateBackup": "14/12/2021 11:25:46",
  "SaveTime": null
}
{
  "DName": "Aled",
  "DSize": 374131244,
  "DSource": "C:\\www\\Aled",
  "DTarget": "C:\\www\\Aled_Backup",
  "DTime": "00:00:00.42",
  "DTransferTime": null,
  "FileName": null,
  "FileSize": null,
  "SourceFolder": null,
  "TargetFolder": null,
  "DateBackup": "14/12/2021 12:36:17",
  "SaveTime": null
}
{
  "DName": "Aled",
  "DSize": 1421834375,
  "DSource": "C:\\www\\Aled",
  "DTarget": "C:\\www\\Aled_Backup",
  "DTime": "00:00:01.10",
  "DTransferTime": null,
  "FileName": null,
  "FileSize": null,
  "SourceFolder": null,
  "TargetFolder": null,
  "DateBackup": "14/12/2021 12:38:01",
  "SaveTime": null
}
{
  "DName": "Aled",
  "DSize": 1421834375,
  "DSource": "C:\\www\\Aled",
  "DTarget": "C:\\www\\Aled_Backup",
  "DTime": "00:00:11.61",
  "DTransferTime": null,
  "FileName": null,
  "FileSize": null,
  "SourceFolder": null,
  "TargetFolder": null,
  "DateBackup": "14/12/2021 12:41:08",
  "SaveTime": null
}
{
  "DName": "Aled",
  "DSize": 1421834375,
  "DSource": "C:\\www\\Aled",
  "DTarget": "C:\\www\\Aled_Backup",
  "DTime": "00:00:48.09",
  "DTransferTime": null,
  "FileName": null,
  "FileSize": null,
  "SourceFolder": null,
  "TargetFolder": null,
  "DateBackup": "14/12/2021 12:42:15",
  "SaveTime": null
}
